{
    "first": {
        "name": "WebRender",
        "description": "Outil de visualisation 3D de modèles/animation/FX en WebGL.<br><br>Basé sur Unity, ce petit outil modulaire vous permet de visualiser vos créations sur votre site internet.",
        "imgUrl": "/img/black-texture.jpg",
        "pageName": "/pages/realization.html?page=WebRender"
    },

    "second": {
        "name": "",
        "description": "",
        "imgUrl": "",
        "pageName": ""
    },

    "third": {
        "name": "",
        "description": "",
        "imgUrl": "",
        "pageName": ""
    }
}